ZetcodeSpringBootJiaochengChuyiFix1/README.md
ZetcodeSpringBootJiaochengChuyiFix1/__init__.py
ZetcodeSpringBootJiaochengChuyiFix1/__main__.py
ZetcodeSpringBootJiaochengChuyiFix1/file.epub
ZetcodeSpringBootJiaochengChuyiFix1/index.html
ZetcodeSpringBootJiaochengChuyiFix1/css/__init__.py
ZetcodeSpringBootJiaochengChuyiFix1/css/annotations.css
ZetcodeSpringBootJiaochengChuyiFix1/css/main.css
ZetcodeSpringBootJiaochengChuyiFix1/css/normalize.css
ZetcodeSpringBootJiaochengChuyiFix1/css/popup.css
ZetcodeSpringBootJiaochengChuyiFix1/font/__init__.py
ZetcodeSpringBootJiaochengChuyiFix1/font/fontello.eot
ZetcodeSpringBootJiaochengChuyiFix1/font/fontello.svg
ZetcodeSpringBootJiaochengChuyiFix1/font/fontello.ttf
ZetcodeSpringBootJiaochengChuyiFix1/font/fontello.woff
ZetcodeSpringBootJiaochengChuyiFix1/img/__init__.py
ZetcodeSpringBootJiaochengChuyiFix1/img/annotator-glyph-sprite.png
ZetcodeSpringBootJiaochengChuyiFix1/img/annotator-icon-sprite.png
ZetcodeSpringBootJiaochengChuyiFix1/img/apple-touch-icon.png
ZetcodeSpringBootJiaochengChuyiFix1/img/cancelfullscreen.png
ZetcodeSpringBootJiaochengChuyiFix1/img/close.png
ZetcodeSpringBootJiaochengChuyiFix1/img/fullscreen.png
ZetcodeSpringBootJiaochengChuyiFix1/img/loader.gif
ZetcodeSpringBootJiaochengChuyiFix1/img/menu-icon.png
ZetcodeSpringBootJiaochengChuyiFix1/img/save.png
ZetcodeSpringBootJiaochengChuyiFix1/img/saved.png
ZetcodeSpringBootJiaochengChuyiFix1/img/settings-s.png
ZetcodeSpringBootJiaochengChuyiFix1/img/settings.png
ZetcodeSpringBootJiaochengChuyiFix1/img/star.png
ZetcodeSpringBootJiaochengChuyiFix1/js/__init__.py
ZetcodeSpringBootJiaochengChuyiFix1/js/epub.js
ZetcodeSpringBootJiaochengChuyiFix1/js/epub.min.js
ZetcodeSpringBootJiaochengChuyiFix1/js/epub.min.map
ZetcodeSpringBootJiaochengChuyiFix1/js/hooks.min.js
ZetcodeSpringBootJiaochengChuyiFix1/js/hooks.min.map
ZetcodeSpringBootJiaochengChuyiFix1/js/reader.js
ZetcodeSpringBootJiaochengChuyiFix1/js/reader.js.map
ZetcodeSpringBootJiaochengChuyiFix1/js/reader.min.js
zetcode_spring_boot_jiaocheng_chuyi_fix1-2025.3.24.1.dist-info/METADATA
zetcode_spring_boot_jiaocheng_chuyi_fix1-2025.3.24.1.dist-info/WHEEL
zetcode_spring_boot_jiaocheng_chuyi_fix1-2025.3.24.1.dist-info/entry_points.txt
zetcode_spring_boot_jiaocheng_chuyi_fix1-2025.3.24.1.dist-info/top_level.txt
zetcode_spring_boot_jiaocheng_chuyi_fix1-2025.3.24.1.dist-info/RECORD
